kylearn/01_basics/__init__.py
kylearn/01_basics/comments.py
kylearn/01_basics/exercises.py
kylearn/01_basics/operators.py
kylearn/01_basics/variables.py
kylearn/02_control_flow/__init__.py
kylearn/02_control_flow/conditions.py
kylearn/02_control_flow/exercises.py
kylearn/02_control_flow/flow_control.py
kylearn/02_control_flow/loops.py
kylearn/03_data_structures/__init__.py
kylearn/03_data_structures/comparison.py
kylearn/03_data_structures/dictionaries.py
kylearn/03_data_structures/exercises.py
kylearn/03_data_structures/lists.py
kylearn/03_data_structures/sets.py
kylearn/03_data_structures/tuples.py
kylearn/04_functions/__init__.py
kylearn/04_functions/advanced_functions.py
kylearn/04_functions/basic_functions.py
kylearn/04_functions/exercises.py
kylearn/04_functions/parameters.py
kylearn/05_oop/__init__.py
kylearn/05_oop/classes_objects.py
kylearn/05_oop/encapsulation.py
kylearn/05_oop/exercises.py
kylearn/05_oop/inheritance.py
kylearn/05_oop/polymorphism.py
kylearn/06_advanced/__init__.py
kylearn/06_advanced/exceptions.py
kylearn/06_advanced/modules.py
kylearn/__init__.md
kylearn/__init__.py
kylearn/__main__.py
kylearn/decorators/singleton.py
kylearn/learning_guide.py
kylearn-0.1.5.dist-info/WHEEL
kylearn-0.1.5.dist-info/entry_points.txt
kylearn-0.1.5.dist-info/METADATA
kylearn-0.1.5.dist-info/RECORD
